LICENSE.txt
MANIFEST.in
README.md
setup.cfg
setup.py
tests/__init__.py
tests/test_add.py
tests/test_finals.py
tests/test_has.py
tests/test_initials.py
tests/test_regex.py
tests/test_remove.py
tests/test_trieregex.py
trieregex/__init__.py
trieregex/memoizer.py
trieregex/trieregex.py
trieregex.egg-info/PKG-INFO
trieregex.egg-info/SOURCES.txt
trieregex.egg-info/dependency_links.txt
trieregex.egg-info/requires.txt
trieregex.egg-info/top_level.txt