Metadata-Version: 2.1
Name: trieregex
Version: 1.0.0
Summary: Build trie-based regular expressions from large word lists
Home-page: https://github.com/ermanh/trieregex
Author: Herman Leung
Author-email: leung.hm@gmail.com
License: MIT
Keywords: regular expressions,regex,pattern,trie
Platform: UNKNOWN
Classifier: Development Status :: 5 - Production/Stable
Classifier: Intended Audience :: Developers
Classifier: License :: OSI Approved :: MIT License
Classifier: Operating System :: OS Independent
Classifier: Programming Language :: Python
Classifier: Programming Language :: Python :: 3
Classifier: Programming Language :: Python :: 3.6
Classifier: Programming Language :: Python :: 3.7
Classifier: Programming Language :: Python :: 3.8
Requires-Python: >=3.6
Provides-Extra: testing
